mailrise/__init__.py
mailrise/basic_authenticator.py
mailrise/config.py
mailrise/py.typed
mailrise/router.py
mailrise/simple_router.py
mailrise/skeleton.py
mailrise/smtp.py
mailrise/asset/homelab-diagram.png
mailrise/asset/homelab-diagram.svg
mailrise/asset/mailrise-failure-128x128.ico
mailrise/asset/mailrise-failure-128x128.png
mailrise/asset/mailrise-failure-256x256.png
mailrise/asset/mailrise-failure-32x32.png
mailrise/asset/mailrise-failure-72x72.png
mailrise/asset/mailrise-info-128x128.ico
mailrise/asset/mailrise-info-128x128.png
mailrise/asset/mailrise-info-256x256.png
mailrise/asset/mailrise-info-32x32.png
mailrise/asset/mailrise-info-72x72.png
mailrise/asset/mailrise-logo.png
mailrise/asset/mailrise-logo.svg
mailrise/asset/mailrise-success-128x128.ico
mailrise/asset/mailrise-success-128x128.png
mailrise/asset/mailrise-success-256x256.png
mailrise/asset/mailrise-success-32x32.png
mailrise/asset/mailrise-success-72x72.png
mailrise/asset/mailrise-warning-128x128.ico
mailrise/asset/mailrise-warning-128x128.png
mailrise/asset/mailrise-warning-256x256.png
mailrise/asset/mailrise-warning-32x32.png
mailrise/asset/mailrise-warning-72x72.png
mailrise-1.4.0.dist-info/AUTHORS.rst
mailrise-1.4.0.dist-info/LICENSE.txt
mailrise-1.4.0.dist-info/METADATA
mailrise-1.4.0.dist-info/WHEEL
mailrise-1.4.0.dist-info/entry_points.txt
mailrise-1.4.0.dist-info/top_level.txt
mailrise-1.4.0.dist-info/RECORD
