Metadata-Version: 2.1
Name: mailrise
Version: 1.4.0
Summary: An SMTP gateway for Apprise notifications.
Home-page: https://mailrise.xyz
Author: Ryan Young
Author-email: ryan@youngryan.com
License: MIT
Project-URL: Documentation, https://pyscaffold.org/
Platform: any
Classifier: Development Status :: 5 - Production/Stable
Classifier: Programming Language :: Python
Classifier: Programming Language :: Python :: 3
Classifier: License :: OSI Approved :: MIT License
Classifier: Topic :: Communications :: Email
Classifier: Environment :: No Input/Output (Daemon)
Classifier: Intended Audience :: System Administrators
Classifier: Operating System :: POSIX :: Linux
Classifier: Operating System :: Microsoft :: Windows
Requires-Python: >=3.8
License-File: LICENSE.txt
License-File: AUTHORS.rst
Requires-Dist: apprise (==1.4.5)
Requires-Dist: aiosmtpd (==1.4.4.post2)
Requires-Dist: PyYAML (==6.0)
Provides-Extra: testing
Requires-Dist: setuptools ; extra == 'testing'
Requires-Dist: types-PyYAML ; extra == 'testing'
Requires-Dist: pytest ; extra == 'testing'
Requires-Dist: pytest-asyncio ; extra == 'testing'
Requires-Dist: pytest-cov ; extra == 'testing'
